entrypoint2/__init__.py
entrypoint2/about.py
entrypoint2/py.typed
entrypoint2/check/__init__.py
entrypoint2/check/defaults.py
entrypoint2/check/hints.py
entrypoint2/examples/__init__.py
entrypoint2/examples/add.py
entrypoint2/examples/caller.py
entrypoint2/examples/defaultvalues.py
entrypoint2/examples/hello.py
entrypoint2/examples/repeating.py
entrypoint2/examples/typehints.py
entrypoint2/examples/varargs.py
entrypoint2-1.0.dist-info/LICENSE.txt
entrypoint2-1.0.dist-info/METADATA
entrypoint2-1.0.dist-info/WHEEL
entrypoint2-1.0.dist-info/top_level.txt
entrypoint2-1.0.dist-info/RECORD
