Metadata-Version: 2.1
Name: entrypoint2
Version: 1.0
Summary: easy to use command-line interface for python modules
Home-page: https://github.com/ponty/entrypoint2
Author: ponty
License: BSD
Keywords: argparse decorator optparse signature command-line
Platform: UNKNOWN
Classifier: License :: OSI Approved :: BSD License
Classifier: Natural Language :: English
Classifier: Operating System :: OS Independent
Classifier: Programming Language :: Python
Classifier: Programming Language :: Python :: 3
Classifier: Programming Language :: Python :: 3 :: Only
Classifier: Programming Language :: Python :: 3.6
Classifier: Programming Language :: Python :: 3.7
Classifier: Programming Language :: Python :: 3.8
Classifier: Programming Language :: Python :: 3.9
Classifier: Programming Language :: Python :: 3.10
